<?xml version="1.0" encoding="UTF-8"?>
<root xmlns:xsi="http://www.w3.org/2001/XMLSchema-instance" xsi:noNamespaceSchemaLocation="WeAllWalk.xsd">
<PathID>1</PathID>
<SubjectID>8</SubjectID>
<MobilityTool>WC</MobilityTool>
<SubjectAnnotations>The participant is a proficient traveler. She often veered off the straight direction when walking in a corridor and had to correct her path</SubjectAnnotations>
<OtherAnnotations>The participant used a white cane with pencil tip. She taps the cane in 2-point touch</OtherAnnotations>
<OtherAnnotations>The participant had to shoreline a lot and often got caught in wall openings</OtherAnnotations>
<Segments>
<PathSegment>
	<PathSegmentID>1</PathSegmentID>
	<SpatialSegmentID>1</SpatialSegmentID>
	<StartTime>1.9484</StartTime>
	<EndTime>10.1427</EndTime>
	<NSteps>12</NSteps>
	<Direction>E</Direction>
	<Steps>
		<Step>
			<WhichFoot>L</WhichFoot>
			<Time>3.5394</Time>
		</Step>
		<Step>
			<WhichFoot>R</WhichFoot>
			<Time>4.0780</Time>
		</Step>
		<Step>
			<WhichFoot>L</WhichFoot>
			<Time>4.6474</Time>
		</Step>
		<Step>
			<WhichFoot>R</WhichFoot>
			<Time>5.2491</Time>
		</Step>
		<Step>
			<WhichFoot>L</WhichFoot>
			<Time>5.8780</Time>
		</Step>
		<Step>
			<WhichFoot>R</WhichFoot>
			<Time>6.4478</Time>
		</Step>
		<Step>
			<WhichFoot>L</WhichFoot>
			<Time>7.0493</Time>
		</Step>
		<Step>
			<WhichFoot>R</WhichFoot>
			<Time>7.5590</Time>
		</Step>
		<Step>
			<WhichFoot>L</WhichFoot>
			<Time>8.2216</Time>
		</Step>
		<Step>
			<WhichFoot>R</WhichFoot>
			<Time>8.7876</Time>
		</Step>
		<Step>
			<WhichFoot>L</WhichFoot>
			<Time>9.4237</Time>
		</Step>
		<Step>
			<WhichFoot>R</WhichFoot>
			<Time>9.9282</Time>
		</Step>
	</Steps>
</PathSegment>
<PathSegment>
	<PathSegmentID>2</PathSegmentID>
	<SpatialSegmentID>1-5</SpatialSegmentID>
	<StartTime>10.1427</StartTime>
	<EndTime>16.7973</EndTime>
	<NSteps>2</NSteps>
	<Direction>TurnEtoS</Direction>
	<TurnTime>12.3600</TurnTime>
	<TurnInDegrees>-90</TurnInDegrees>
	<Steps>
		<Step>
			<WhichFoot>L</WhichFoot>
			<Time>10.5029</Time>
		</Step>
	</Steps>
</PathSegment>
<PathSegment>
	<PathSegmentID>3</PathSegmentID>
	<SpatialSegmentID>5</SpatialSegmentID>
	<StartTime>16.7973</StartTime>
	<EndTime>28.7978</EndTime>
	<NSteps>20</NSteps>
	<Direction>S</Direction>
	<Steps>
		<Step>
			<WhichFoot>R</WhichFoot>
			<Time>17.0985</Time>
		</Step>
		<Step>
			<WhichFoot>L</WhichFoot>
			<Time>17.7273</Time>
		</Step>
		<Step>
			<WhichFoot>R</WhichFoot>
			<Time>18.3308</Time>
		</Step>
		<Step>
			<WhichFoot>L</WhichFoot>
			<Time>18.8684</Time>
		</Step>
		<Step>
			<WhichFoot>R</WhichFoot>
			<Time>19.4378</Time>
		</Step>
		<Step>
			<WhichFoot>L</WhichFoot>
			<Time>20.0676</Time>
		</Step>
		<Step>
			<WhichFoot>R</WhichFoot>
			<Time>20.6676</Time>
		</Step>
		<Step>
			<WhichFoot>L</WhichFoot>
			<Time>21.2374</Time>
		</Step>
		<Step>
			<WhichFoot>R</WhichFoot>
			<Time>21.8375</Time>
		</Step>
		<Step>
			<WhichFoot>L</WhichFoot>
			<Time>22.5029</Time>
		</Step>
		<Step>
			<WhichFoot>R</WhichFoot>
			<Time>23.0987</Time>
		</Step>
		<Step>
			<WhichFoot>L</WhichFoot>
			<Time>23.7582</Time>
		</Step>
		<Step>
			<WhichFoot>R</WhichFoot>
			<Time>24.3381</Time>
		</Step>
		<Step>
			<WhichFoot>L</WhichFoot>
			<Time>24.9282</Time>
		</Step>
		<Step>
			<WhichFoot>R</WhichFoot>
			<Time>25.4683</Time>
		</Step>
		<Step>
			<WhichFoot>L</WhichFoot>
			<Time>26.0391</Time>
		</Step>
		<Step>
			<WhichFoot>R</WhichFoot>
			<Time>26.5781</Time>
		</Step>
		<Step>
			<WhichFoot>L</WhichFoot>
			<Time>27.2223</Time>
		</Step>
		<Step>
			<WhichFoot>R</WhichFoot>
			<Time>27.7781</Time>
		</Step>
		<Step>
			<WhichFoot>L</WhichFoot>
			<Time>28.3475</Time>
		</Step>
	</Steps>
</PathSegment>
<PathSegment>
	<PathSegmentID>4</PathSegmentID>
	<SpatialSegmentID>5-8</SpatialSegmentID>
	<StartTime>28.7978</StartTime>
	<EndTime>44.1274</EndTime>
	<NSteps>15</NSteps>
	<Direction>TurnStoE</Direction>
	<TurnTime>38.7600</TurnTime>
	<TurnInDegrees>90</TurnInDegrees>
	<Steps>
		<Step>
			<WhichFoot>L</WhichFoot>
			<Time>29.7593</Time>
		</Step>
		<Step>
			<WhichFoot>R</WhichFoot>
			<Time>34.1800</Time>
		</Step>
		<Step>
			<WhichFoot>L</WhichFoot>
			<Time>34.7992</Time>
		</Step>
		<Step>
			<WhichFoot>R</WhichFoot>
			<Time>35.6082</Time>
		</Step>
		<Step>
			<WhichFoot>L</WhichFoot>
			<Time>36.2400</Time>
		</Step>
		<Step>
			<WhichFoot>R</WhichFoot>
			<Time>37.1094</Time>
		</Step>
		<Step>
			<WhichFoot>L</WhichFoot>
			<Time>37.8877</Time>
		</Step>
		<Step>
			<WhichFoot>R</WhichFoot>
			<Time>38.5481</Time>
		</Step>
		<Step>
			<WhichFoot>L</WhichFoot>
			<Time>39.2391</Time>
		</Step>
		<Step>
			<WhichFoot>R</WhichFoot>
			<Time>39.7782</Time>
		</Step>
		<Step>
			<WhichFoot>L</WhichFoot>
			<Time>40.4231</Time>
		</Step>
		<Step>
			<WhichFoot>R</WhichFoot>
			<Time>40.9477</Time>
		</Step>
		<Step>
			<WhichFoot>R</WhichFoot>
			<Time>42.6281</Time>
		</Step>
		<Step>
			<WhichFoot>L</WhichFoot>
			<Time>43.3184</Time>
		</Step>
		<Step>
			<WhichFoot>R</WhichFoot>
			<Time>43.8287</Time>
		</Step>
	</Steps>
</PathSegment>
<PathSegment>
	<PathSegmentID>5</PathSegmentID>
	<SpatialSegmentID>8</SpatialSegmentID>
	<StartTime>44.1274</StartTime>
	<EndTime>83.7897</EndTime>
	<NSteps>70</NSteps>
	<Direction>E</Direction>
	<Steps>
		<Step>
			<WhichFoot>L</WhichFoot>
			<Time>44.4906</Time>
		</Step>
		<Step>
			<WhichFoot>R</WhichFoot>
			<Time>45.0000</Time>
		</Step>
		<Step>
			<WhichFoot>L</WhichFoot>
			<Time>45.6621</Time>
		</Step>
		<Step>
			<WhichFoot>R</WhichFoot>
			<Time>46.2295</Time>
		</Step>
		<Step>
			<WhichFoot>L</WhichFoot>
			<Time>46.9207</Time>
		</Step>
		<Step>
			<WhichFoot>R</WhichFoot>
			<Time>47.4612</Time>
		</Step>
		<Step>
			<WhichFoot>L</WhichFoot>
			<Time>48.0642</Time>
		</Step>
		<Step>
			<WhichFoot>R</WhichFoot>
			<Time>48.5977</Time>
		</Step>
		<Step>
			<WhichFoot>L</WhichFoot>
			<Time>49.2284</Time>
		</Step>
		<Step>
			<WhichFoot>R</WhichFoot>
			<Time>49.7378</Time>
		</Step>
		<Step>
			<WhichFoot>L</WhichFoot>
			<Time>50.3432</Time>
		</Step>
		<Step>
			<WhichFoot>R</WhichFoot>
			<Time>50.8493</Time>
		</Step>
		<Step>
			<WhichFoot>L</WhichFoot>
			<Time>51.4485</Time>
		</Step>
		<Step>
			<WhichFoot>R</WhichFoot>
			<Time>51.9577</Time>
		</Step>
		<Step>
			<WhichFoot>L</WhichFoot>
			<Time>52.6244</Time>
		</Step>
		<Step>
			<WhichFoot>R</WhichFoot>
			<Time>53.0997</Time>
		</Step>
		<Step>
			<WhichFoot>L</WhichFoot>
			<Time>53.7000</Time>
		</Step>
		<Step>
			<WhichFoot>R</WhichFoot>
			<Time>54.2186</Time>
		</Step>
		<Step>
			<WhichFoot>L</WhichFoot>
			<Time>54.8980</Time>
		</Step>
		<Step>
			<WhichFoot>R</WhichFoot>
			<Time>55.4382</Time>
		</Step>
		<Step>
			<WhichFoot>L</WhichFoot>
			<Time>55.9477</Time>
		</Step>
		<Step>
			<WhichFoot>R</WhichFoot>
			<Time>56.5202</Time>
		</Step>
		<Step>
			<WhichFoot>L</WhichFoot>
			<Time>57.0880</Time>
		</Step>
		<Step>
			<WhichFoot>R</WhichFoot>
			<Time>57.6607</Time>
		</Step>
		<Step>
			<WhichFoot>L</WhichFoot>
			<Time>58.2285</Time>
		</Step>
		<Step>
			<WhichFoot>R</WhichFoot>
			<Time>58.7976</Time>
		</Step>
		<Step>
			<WhichFoot>L</WhichFoot>
			<Time>59.3075</Time>
		</Step>
		<Step>
			<WhichFoot>R</WhichFoot>
			<Time>59.8801</Time>
		</Step>
		<Step>
			<WhichFoot>L</WhichFoot>
			<Time>60.4484</Time>
		</Step>
		<Step>
			<WhichFoot>R</WhichFoot>
			<Time>60.9891</Time>
		</Step>
		<Step>
			<WhichFoot>L</WhichFoot>
			<Time>61.5597</Time>
		</Step>
		<Step>
			<WhichFoot>R</WhichFoot>
			<Time>62.0693</Time>
		</Step>
		<Step>
			<WhichFoot>L</WhichFoot>
			<Time>62.7025</Time>
		</Step>
		<Step>
			<WhichFoot>R</WhichFoot>
			<Time>63.1778</Time>
		</Step>
		<Step>
			<WhichFoot>L</WhichFoot>
			<Time>63.7827</Time>
		</Step>
		<Step>
			<WhichFoot>R</WhichFoot>
			<Time>64.2890</Time>
		</Step>
		<Step>
			<WhichFoot>L</WhichFoot>
			<Time>64.9176</Time>
		</Step>
		<Step>
			<WhichFoot>R</WhichFoot>
			<Time>65.4294</Time>
		</Step>
		<Step>
			<WhichFoot>L</WhichFoot>
			<Time>66.0588</Time>
		</Step>
		<Step>
			<WhichFoot>R</WhichFoot>
			<Time>66.5398</Time>
		</Step>
		<Step>
			<WhichFoot>L</WhichFoot>
			<Time>67.1974</Time>
		</Step>
		<Step>
			<WhichFoot>R</WhichFoot>
			<Time>67.7395</Time>
		</Step>
		<Step>
			<WhichFoot>L</WhichFoot>
			<Time>68.3088</Time>
		</Step>
		<Step>
			<WhichFoot>R</WhichFoot>
			<Time>68.8582</Time>
		</Step>
		<Step>
			<WhichFoot>L</WhichFoot>
			<Time>69.4493</Time>
		</Step>
		<Step>
			<WhichFoot>R</WhichFoot>
			<Time>69.9877</Time>
		</Step>
		<Step>
			<WhichFoot>L</WhichFoot>
			<Time>70.6232</Time>
		</Step>
		<Step>
			<WhichFoot>R</WhichFoot>
			<Time>71.1873</Time>
		</Step>
		<Step>
			<WhichFoot>L</WhichFoot>
			<Time>71.7029</Time>
		</Step>
		<Step>
			<WhichFoot>R</WhichFoot>
			<Time>72.2693</Time>
		</Step>
		<Step>
			<WhichFoot>L</WhichFoot>
			<Time>72.8702</Time>
		</Step>
		<Step>
			<WhichFoot>R</WhichFoot>
			<Time>73.3779</Time>
		</Step>
		<Step>
			<WhichFoot>L</WhichFoot>
			<Time>74.0094</Time>
		</Step>
		<Step>
			<WhichFoot>R</WhichFoot>
			<Time>74.5779</Time>
		</Step>
		<Step>
			<WhichFoot>L</WhichFoot>
			<Time>75.1180</Time>
		</Step>
		<Step>
			<WhichFoot>R</WhichFoot>
			<Time>75.6298</Time>
		</Step>
		<Step>
			<WhichFoot>L</WhichFoot>
			<Time>76.2585</Time>
		</Step>
		<Step>
			<WhichFoot>R</WhichFoot>
			<Time>76.7388</Time>
		</Step>
		<Step>
			<WhichFoot>L</WhichFoot>
			<Time>77.3427</Time>
		</Step>
		<Step>
			<WhichFoot>R</WhichFoot>
			<Time>77.8829</Time>
		</Step>
		<Step>
			<WhichFoot>L</WhichFoot>
			<Time>78.5072</Time>
		</Step>
		<Step>
			<WhichFoot>R</WhichFoot>
			<Time>78.9882</Time>
		</Step>
		<Step>
			<WhichFoot>L</WhichFoot>
			<Time>79.6232</Time>
		</Step>
		<Step>
			<WhichFoot>R</WhichFoot>
			<Time>80.0989</Time>
		</Step>
		<Step>
			<WhichFoot>L</WhichFoot>
			<Time>80.7029</Time>
		</Step>
		<Step>
			<WhichFoot>R</WhichFoot>
			<Time>81.2074</Time>
		</Step>
		<Step>
			<WhichFoot>L</WhichFoot>
			<Time>81.7831</Time>
		</Step>
		<Step>
			<WhichFoot>R</WhichFoot>
			<Time>82.3192</Time>
		</Step>
		<Step>
			<WhichFoot>L</WhichFoot>
			<Time>82.9193</Time>
		</Step>
		<Step>
			<WhichFoot>R</WhichFoot>
			<Time>83.4713</Time>
		</Step>
	</Steps>
</PathSegment>
<PathSegment>
	<PathSegmentID>6</PathSegmentID>
	<SpatialSegmentID>8-10</SpatialSegmentID>
	<StartTime>83.7897</StartTime>
	<EndTime>87.5698</EndTime>
	<NSteps>3</NSteps>
	<Direction>TurnEtoS</Direction>
	<TurnTime>85.1600</TurnTime>
	<TurnInDegrees>-90</TurnInDegrees>
	<Steps>
		<Step>
			<WhichFoot>L</WhichFoot>
			<Time>84.0636</Time>
		</Step>
		<Step>
			<WhichFoot>L</WhichFoot>
			<Time>85.8282</Time>
		</Step>
		<Step>
			<WhichFoot>L</WhichFoot>
			<Time>87.2095</Time>
		</Step>
	</Steps>
</PathSegment>
<PathSegment>
	<PathSegmentID>7</PathSegmentID>
	<SpatialSegmentID>10</SpatialSegmentID>
	<StartTime>87.5698</StartTime>
	<EndTime>93.9883</EndTime>
	<NSteps>10</NSteps>
	<Direction>S</Direction>
	<Steps>
		<Step>
			<WhichFoot>R</WhichFoot>
			<Time>87.8678</Time>
		</Step>
		<Step>
			<WhichFoot>L</WhichFoot>
			<Time>88.5312</Time>
		</Step>
		<Step>
			<WhichFoot>R</WhichFoot>
			<Time>89.1291</Time>
		</Step>
		<Step>
			<WhichFoot>L</WhichFoot>
			<Time>89.7891</Time>
		</Step>
		<Step>
			<WhichFoot>R</WhichFoot>
			<Time>90.3879</Time>
		</Step>
		<Step>
			<WhichFoot>L</WhichFoot>
			<Time>90.9890</Time>
		</Step>
		<Step>
			<WhichFoot>R</WhichFoot>
			<Time>91.5000</Time>
		</Step>
		<Step>
			<WhichFoot>L</WhichFoot>
			<Time>92.1026</Time>
		</Step>
		<Step>
			<WhichFoot>R</WhichFoot>
			<Time>92.7576</Time>
		</Step>
		<Step>
			<WhichFoot>L</WhichFoot>
			<Time>93.2685</Time>
		</Step>
	</Steps>
</PathSegment>
</Segments>
</root>
