<?xml version="1.0" encoding="UTF-8"?>
<root xmlns:xsi="http://www.w3.org/2001/XMLSchema-instance" xsi:noNamespaceSchemaLocation="WeAllWalk.xsd">
<PathID>4</PathID>
<SubjectID>14</SubjectID>
<MobilityTool>NA</MobilityTool>
<SubjectAnnotations>A sighted participant</SubjectAnnotations>
<OtherAnnotations>Data from sighted participants was only added as a “control,” for comparison in identical settings</OtherAnnotations>
<Segments>
<PathSegment>
	<PathSegmentID>1</PathSegmentID>
	<SpatialSegmentID>10-6</SpatialSegmentID>
	<StartTime>5.1397</StartTime>
	<EndTime>18.3397</EndTime>
	<NSteps>20</NSteps>
	<Direction>N</Direction>
	<Steps>
		<Step>
			<WhichFoot>R</WhichFoot>
			<Time>6.1825</Time>
		</Step>
		<Step>
			<WhichFoot>L</WhichFoot>
			<Time>6.7799</Time>
		</Step>
		<Step>
			<WhichFoot>R</WhichFoot>
			<Time>7.4709</Time>
		</Step>
		<Step>
			<WhichFoot>L</WhichFoot>
			<Time>8.0686</Time>
		</Step>
		<Step>
			<WhichFoot>R</WhichFoot>
			<Time>8.7013</Time>
		</Step>
		<Step>
			<WhichFoot>L</WhichFoot>
			<Time>9.3001</Time>
		</Step>
		<Step>
			<WhichFoot>R</WhichFoot>
			<Time>9.9624</Time>
		</Step>
		<Step>
			<WhichFoot>L</WhichFoot>
			<Time>10.4996</Time>
		</Step>
		<Step>
			<WhichFoot>R</WhichFoot>
			<Time>11.2239</Time>
		</Step>
		<Step>
			<WhichFoot>L</WhichFoot>
			<Time>11.8487</Time>
		</Step>
		<Step>
			<WhichFoot>R</WhichFoot>
			<Time>12.4199</Time>
		</Step>
		<Step>
			<WhichFoot>L</WhichFoot>
			<Time>12.9296</Time>
		</Step>
		<Step>
			<WhichFoot>R</WhichFoot>
			<Time>13.6609</Time>
		</Step>
		<Step>
			<WhichFoot>L</WhichFoot>
			<Time>14.1601</Time>
		</Step>
		<Step>
			<WhichFoot>R</WhichFoot>
			<Time>14.7903</Time>
		</Step>
		<Step>
			<WhichFoot>L</WhichFoot>
			<Time>15.3006</Time>
		</Step>
		<Step>
			<WhichFoot>R</WhichFoot>
			<Time>16.0197</Time>
		</Step>
		<Step>
			<WhichFoot>L</WhichFoot>
			<Time>16.5308</Time>
		</Step>
		<Step>
			<WhichFoot>R</WhichFoot>
			<Time>17.2568</Time>
		</Step>
		<Step>
			<WhichFoot>L</WhichFoot>
			<Time>17.7591</Time>
		</Step>
	</Steps>
</PathSegment>
<PathSegment>
	<PathSegmentID>2</PathSegmentID>
	<SpatialSegmentID>10-6-3</SpatialSegmentID>
	<StartTime>18.3397</StartTime>
	<EndTime>21.3730</EndTime>
	<NSteps>5</NSteps>
	<Direction>TurnNtoE</Direction>
	<TurnTime>20.6400</TurnTime>
	<TurnInDegrees>-90</TurnInDegrees>
	<Steps>
		<Step>
			<WhichFoot>R</WhichFoot>
			<Time>18.4194</Time>
		</Step>
		<Step>
			<WhichFoot>L</WhichFoot>
			<Time>18.8991</Time>
		</Step>
		<Step>
			<WhichFoot>R</WhichFoot>
			<Time>19.5309</Time>
		</Step>
		<Step>
			<WhichFoot>L</WhichFoot>
			<Time>20.1000</Time>
		</Step>
		<Step>
			<WhichFoot>R</WhichFoot>
			<Time>20.7897</Time>
		</Step>
	</Steps>
</PathSegment>
<PathSegment>
	<PathSegmentID>3</PathSegmentID>
	<SpatialSegmentID>3</SpatialSegmentID>
	<StartTime>21.3730</StartTime>
	<EndTime>74.4397</EndTime>
	<NSteps>93</NSteps>
	<Direction>E</Direction>
	<Steps>
		<Step>
			<WhichFoot>L</WhichFoot>
			<Time>21.3609</Time>
		</Step>
		<Step>
			<WhichFoot>R</WhichFoot>
			<Time>22.0208</Time>
		</Step>
		<Step>
			<WhichFoot>L</WhichFoot>
			<Time>22.5591</Time>
		</Step>
		<Step>
			<WhichFoot>R</WhichFoot>
			<Time>23.2794</Time>
		</Step>
		<Step>
			<WhichFoot>L</WhichFoot>
			<Time>23.8515</Time>
		</Step>
		<Step>
			<WhichFoot>R</WhichFoot>
			<Time>24.4799</Time>
		</Step>
		<Step>
			<WhichFoot>L</WhichFoot>
			<Time>24.9898</Time>
		</Step>
		<Step>
			<WhichFoot>R</WhichFoot>
			<Time>25.6567</Time>
		</Step>
		<Step>
			<WhichFoot>L</WhichFoot>
			<Time>26.1591</Time>
		</Step>
		<Step>
			<WhichFoot>R</WhichFoot>
			<Time>26.8606</Time>
		</Step>
		<Step>
			<WhichFoot>L</WhichFoot>
			<Time>27.3302</Time>
		</Step>
		<Step>
			<WhichFoot>R</WhichFoot>
			<Time>27.9898</Time>
		</Step>
		<Step>
			<WhichFoot>L</WhichFoot>
			<Time>28.5389</Time>
		</Step>
		<Step>
			<WhichFoot>R</WhichFoot>
			<Time>29.1450</Time>
		</Step>
		<Step>
			<WhichFoot>L</WhichFoot>
			<Time>29.6694</Time>
		</Step>
		<Step>
			<WhichFoot>R</WhichFoot>
			<Time>30.3372</Time>
		</Step>
		<Step>
			<WhichFoot>L</WhichFoot>
			<Time>30.8199</Time>
		</Step>
		<Step>
			<WhichFoot>R</WhichFoot>
			<Time>31.4402</Time>
		</Step>
		<Step>
			<WhichFoot>L</WhichFoot>
			<Time>31.9491</Time>
		</Step>
		<Step>
			<WhichFoot>R</WhichFoot>
			<Time>32.6168</Time>
		</Step>
		<Step>
			<WhichFoot>L</WhichFoot>
			<Time>33.1005</Time>
		</Step>
		<Step>
			<WhichFoot>R</WhichFoot>
			<Time>33.7793</Time>
		</Step>
		<Step>
			<WhichFoot>L</WhichFoot>
			<Time>34.2587</Time>
		</Step>
		<Step>
			<WhichFoot>R</WhichFoot>
			<Time>34.9202</Time>
		</Step>
		<Step>
			<WhichFoot>L</WhichFoot>
			<Time>35.3696</Time>
		</Step>
		<Step>
			<WhichFoot>R</WhichFoot>
			<Time>36.0295</Time>
		</Step>
		<Step>
			<WhichFoot>L</WhichFoot>
			<Time>36.5414</Time>
		</Step>
		<Step>
			<WhichFoot>R</WhichFoot>
			<Time>37.1869</Time>
		</Step>
		<Step>
			<WhichFoot>L</WhichFoot>
			<Time>37.7099</Time>
		</Step>
		<Step>
			<WhichFoot>R</WhichFoot>
			<Time>38.3401</Time>
		</Step>
		<Step>
			<WhichFoot>L</WhichFoot>
			<Time>38.8798</Time>
		</Step>
		<Step>
			<WhichFoot>R</WhichFoot>
			<Time>39.5406</Time>
		</Step>
		<Step>
			<WhichFoot>L</WhichFoot>
			<Time>40.0191</Time>
		</Step>
		<Step>
			<WhichFoot>R</WhichFoot>
			<Time>40.6808</Time>
		</Step>
		<Step>
			<WhichFoot>L</WhichFoot>
			<Time>41.2201</Time>
		</Step>
		<Step>
			<WhichFoot>R</WhichFoot>
			<Time>41.8802</Time>
		</Step>
		<Step>
			<WhichFoot>L</WhichFoot>
			<Time>42.3908</Time>
		</Step>
		<Step>
			<WhichFoot>R</WhichFoot>
			<Time>43.0195</Time>
		</Step>
		<Step>
			<WhichFoot>L</WhichFoot>
			<Time>43.5306</Time>
		</Step>
		<Step>
			<WhichFoot>R</WhichFoot>
			<Time>44.1614</Time>
		</Step>
		<Step>
			<WhichFoot>L</WhichFoot>
			<Time>44.6701</Time>
		</Step>
		<Step>
			<WhichFoot>R</WhichFoot>
			<Time>45.3006</Time>
		</Step>
		<Step>
			<WhichFoot>L</WhichFoot>
			<Time>45.7800</Time>
		</Step>
		<Step>
			<WhichFoot>R</WhichFoot>
			<Time>46.3796</Time>
		</Step>
		<Step>
			<WhichFoot>L</WhichFoot>
			<Time>46.9007</Time>
		</Step>
		<Step>
			<WhichFoot>R</WhichFoot>
			<Time>47.5194</Time>
		</Step>
		<Step>
			<WhichFoot>L</WhichFoot>
			<Time>48.1025</Time>
		</Step>
		<Step>
			<WhichFoot>R</WhichFoot>
			<Time>48.7195</Time>
		</Step>
		<Step>
			<WhichFoot>L</WhichFoot>
			<Time>49.2603</Time>
		</Step>
		<Step>
			<WhichFoot>R</WhichFoot>
			<Time>49.8913</Time>
		</Step>
		<Step>
			<WhichFoot>L</WhichFoot>
			<Time>50.3791</Time>
		</Step>
		<Step>
			<WhichFoot>R</WhichFoot>
			<Time>50.9822</Time>
		</Step>
		<Step>
			<WhichFoot>L</WhichFoot>
			<Time>51.4510</Time>
		</Step>
		<Step>
			<WhichFoot>R</WhichFoot>
			<Time>52.1097</Time>
		</Step>
		<Step>
			<WhichFoot>L</WhichFoot>
			<Time>52.6217</Time>
		</Step>
		<Step>
			<WhichFoot>R</WhichFoot>
			<Time>53.2516</Time>
		</Step>
		<Step>
			<WhichFoot>L</WhichFoot>
			<Time>53.7906</Time>
		</Step>
		<Step>
			<WhichFoot>R</WhichFoot>
			<Time>54.3896</Time>
		</Step>
		<Step>
			<WhichFoot>L</WhichFoot>
			<Time>54.8714</Time>
		</Step>
		<Step>
			<WhichFoot>R</WhichFoot>
			<Time>55.5001</Time>
		</Step>
		<Step>
			<WhichFoot>L</WhichFoot>
			<Time>55.9801</Time>
		</Step>
		<Step>
			<WhichFoot>R</WhichFoot>
			<Time>56.6395</Time>
		</Step>
		<Step>
			<WhichFoot>L</WhichFoot>
			<Time>57.1517</Time>
		</Step>
		<Step>
			<WhichFoot>R</WhichFoot>
			<Time>57.7201</Time>
		</Step>
		<Step>
			<WhichFoot>L</WhichFoot>
			<Time>58.2306</Time>
		</Step>
		<Step>
			<WhichFoot>R</WhichFoot>
			<Time>58.8599</Time>
		</Step>
		<Step>
			<WhichFoot>L</WhichFoot>
			<Time>59.3695</Time>
		</Step>
		<Step>
			<WhichFoot>R</WhichFoot>
			<Time>59.9772</Time>
		</Step>
		<Step>
			<WhichFoot>L</WhichFoot>
			<Time>60.4637</Time>
		</Step>
		<Step>
			<WhichFoot>R</WhichFoot>
			<Time>61.0802</Time>
		</Step>
		<Step>
			<WhichFoot>L</WhichFoot>
			<Time>61.5892</Time>
		</Step>
		<Step>
			<WhichFoot>R</WhichFoot>
			<Time>62.1896</Time>
		</Step>
		<Step>
			<WhichFoot>L</WhichFoot>
			<Time>62.6702</Time>
		</Step>
		<Step>
			<WhichFoot>R</WhichFoot>
			<Time>63.3021</Time>
		</Step>
		<Step>
			<WhichFoot>L</WhichFoot>
			<Time>63.7800</Time>
		</Step>
		<Step>
			<WhichFoot>R</WhichFoot>
			<Time>64.3508</Time>
		</Step>
		<Step>
			<WhichFoot>L</WhichFoot>
			<Time>64.8612</Time>
		</Step>
		<Step>
			<WhichFoot>R</WhichFoot>
			<Time>65.4595</Time>
		</Step>
		<Step>
			<WhichFoot>L</WhichFoot>
			<Time>66.0302</Time>
		</Step>
		<Step>
			<WhichFoot>R</WhichFoot>
			<Time>66.6292</Time>
		</Step>
		<Step>
			<WhichFoot>L</WhichFoot>
			<Time>67.1097</Time>
		</Step>
		<Step>
			<WhichFoot>R</WhichFoot>
			<Time>67.7406</Time>
		</Step>
		<Step>
			<WhichFoot>L</WhichFoot>
			<Time>68.2641</Time>
		</Step>
		<Step>
			<WhichFoot>R</WhichFoot>
			<Time>68.7898</Time>
		</Step>
		<Step>
			<WhichFoot>L</WhichFoot>
			<Time>69.2994</Time>
		</Step>
		<Step>
			<WhichFoot>R</WhichFoot>
			<Time>69.9900</Time>
		</Step>
		<Step>
			<WhichFoot>L</WhichFoot>
			<Time>70.4693</Time>
		</Step>
		<Step>
			<WhichFoot>R</WhichFoot>
			<Time>71.0696</Time>
		</Step>
		<Step>
			<WhichFoot>L</WhichFoot>
			<Time>71.5796</Time>
		</Step>
		<Step>
			<WhichFoot>R</WhichFoot>
			<Time>72.2720</Time>
		</Step>
		<Step>
			<WhichFoot>L</WhichFoot>
			<Time>72.7203</Time>
		</Step>
		<Step>
			<WhichFoot>R</WhichFoot>
			<Time>73.3496</Time>
		</Step>
		<Step>
			<WhichFoot>L</WhichFoot>
			<Time>73.9198</Time>
		</Step>
	</Steps>
</PathSegment>
<PathSegment>
	<PathSegmentID>4</PathSegmentID>
	<SpatialSegmentID>3-7</SpatialSegmentID>
	<StartTime>74.4397</StartTime>
	<EndTime>78.3064</EndTime>
	<NSteps>5</NSteps>
	<Direction>TurnEtoS</Direction>
	<TurnTime>75.9600</TurnTime>
	<TurnInDegrees>-90</TurnInDegrees>
	<Steps>
		<Step>
			<WhichFoot>R</WhichFoot>
			<Time>74.6169</Time>
		</Step>
		<Step>
			<WhichFoot>L</WhichFoot>
			<Time>75.1803</Time>
		</Step>
		<Step>
			<WhichFoot>R</WhichFoot>
			<Time>75.9400</Time>
		</Step>
		<Step>
			<WhichFoot>L</WhichFoot>
			<Time>76.8600</Time>
		</Step>
		<Step>
			<WhichFoot>R</WhichFoot>
			<Time>77.7025</Time>
		</Step>
	</Steps>
</PathSegment>
<PathSegment>
	<PathSegmentID>5</PathSegmentID>
	<SpatialSegmentID>7</SpatialSegmentID>
	<StartTime>78.3064</StartTime>
	<EndTime>85.3064</EndTime>
	<NSteps>12</NSteps>
	<Direction>S</Direction>
	<Steps>
		<Step>
			<WhichFoot>L</WhichFoot>
			<Time>78.3002</Time>
		</Step>
		<Step>
			<WhichFoot>R</WhichFoot>
			<Time>79.0218</Time>
		</Step>
		<Step>
			<WhichFoot>L</WhichFoot>
			<Time>79.5902</Time>
		</Step>
		<Step>
			<WhichFoot>R</WhichFoot>
			<Time>80.2206</Time>
		</Step>
		<Step>
			<WhichFoot>L</WhichFoot>
			<Time>80.7595</Time>
		</Step>
		<Step>
			<WhichFoot>R</WhichFoot>
			<Time>81.3907</Time>
		</Step>
		<Step>
			<WhichFoot>L</WhichFoot>
			<Time>81.9012</Time>
		</Step>
		<Step>
			<WhichFoot>R</WhichFoot>
			<Time>82.5903</Time>
		</Step>
		<Step>
			<WhichFoot>L</WhichFoot>
			<Time>83.0693</Time>
		</Step>
		<Step>
			<WhichFoot>R</WhichFoot>
			<Time>83.7297</Time>
		</Step>
		<Step>
			<WhichFoot>L</WhichFoot>
			<Time>84.2397</Time>
		</Step>
		<Step>
			<WhichFoot>R</WhichFoot>
			<Time>84.8698</Time>
		</Step>
	</Steps>
</PathSegment>
<PathSegment>
	<PathSegmentID>6</PathSegmentID>
	<SpatialSegmentID>7-9</SpatialSegmentID>
	<StartTime>85.3064</StartTime>
	<EndTime>88.4730</EndTime>
	<NSteps>5</NSteps>
	<Direction>TurnStoW</Direction>
	<TurnTime>87.6800</TurnTime>
	<TurnInDegrees>-90</TurnInDegrees>
	<Steps>
		<Step>
			<WhichFoot>L</WhichFoot>
			<Time>85.4395</Time>
		</Step>
		<Step>
			<WhichFoot>R</WhichFoot>
			<Time>86.0394</Time>
		</Step>
		<Step>
			<WhichFoot>L</WhichFoot>
			<Time>86.7412</Time>
		</Step>
		<Step>
			<WhichFoot>R</WhichFoot>
			<Time>87.3927</Time>
		</Step>
		<Step>
			<WhichFoot>L</WhichFoot>
			<Time>87.9603</Time>
		</Step>
	</Steps>
</PathSegment>
<PathSegment>
	<PathSegmentID>7</PathSegmentID>
	<SpatialSegmentID>9</SpatialSegmentID>
	<StartTime>88.4730</StartTime>
	<EndTime>141.0730</EndTime>
	<NSteps>92</NSteps>
	<Direction>W</Direction>
	<Steps>
		<Step>
			<WhichFoot>R</WhichFoot>
			<Time>88.5897</Time>
		</Step>
		<Step>
			<WhichFoot>L</WhichFoot>
			<Time>89.1594</Time>
		</Step>
		<Step>
			<WhichFoot>R</WhichFoot>
			<Time>89.8506</Time>
		</Step>
		<Step>
			<WhichFoot>L</WhichFoot>
			<Time>90.5408</Time>
		</Step>
		<Step>
			<WhichFoot>R</WhichFoot>
			<Time>91.1106</Time>
		</Step>
		<Step>
			<WhichFoot>L</WhichFoot>
			<Time>91.7097</Time>
		</Step>
		<Step>
			<WhichFoot>R</WhichFoot>
			<Time>92.3106</Time>
		</Step>
		<Step>
			<WhichFoot>L</WhichFoot>
			<Time>92.7905</Time>
		</Step>
		<Step>
			<WhichFoot>R</WhichFoot>
			<Time>93.4502</Time>
		</Step>
		<Step>
			<WhichFoot>L</WhichFoot>
			<Time>93.9897</Time>
		</Step>
		<Step>
			<WhichFoot>R</WhichFoot>
			<Time>94.5601</Time>
		</Step>
		<Step>
			<WhichFoot>L</WhichFoot>
			<Time>95.1001</Time>
		</Step>
		<Step>
			<WhichFoot>R</WhichFoot>
			<Time>95.6705</Time>
		</Step>
		<Step>
			<WhichFoot>L</WhichFoot>
			<Time>96.1839</Time>
		</Step>
		<Step>
			<WhichFoot>R</WhichFoot>
			<Time>96.8694</Time>
		</Step>
		<Step>
			<WhichFoot>L</WhichFoot>
			<Time>97.3508</Time>
		</Step>
		<Step>
			<WhichFoot>R</WhichFoot>
			<Time>97.9499</Time>
		</Step>
		<Step>
			<WhichFoot>L</WhichFoot>
			<Time>98.4592</Time>
		</Step>
		<Step>
			<WhichFoot>R</WhichFoot>
			<Time>99.1200</Time>
		</Step>
		<Step>
			<WhichFoot>L</WhichFoot>
			<Time>99.6304</Time>
		</Step>
		<Step>
			<WhichFoot>R</WhichFoot>
			<Time>100.2597</Time>
		</Step>
		<Step>
			<WhichFoot>L</WhichFoot>
			<Time>100.8292</Time>
		</Step>
		<Step>
			<WhichFoot>R</WhichFoot>
			<Time>101.4004</Time>
		</Step>
		<Step>
			<WhichFoot>L</WhichFoot>
			<Time>101.9120</Time>
		</Step>
		<Step>
			<WhichFoot>R</WhichFoot>
			<Time>102.5394</Time>
		</Step>
		<Step>
			<WhichFoot>L</WhichFoot>
			<Time>103.0203</Time>
		</Step>
		<Step>
			<WhichFoot>R</WhichFoot>
			<Time>103.7110</Time>
		</Step>
		<Step>
			<WhichFoot>L</WhichFoot>
			<Time>104.2202</Time>
		</Step>
		<Step>
			<WhichFoot>R</WhichFoot>
			<Time>104.8798</Time>
		</Step>
		<Step>
			<WhichFoot>L</WhichFoot>
			<Time>105.3919</Time>
		</Step>
		<Step>
			<WhichFoot>R</WhichFoot>
			<Time>106.0200</Time>
		</Step>
		<Step>
			<WhichFoot>L</WhichFoot>
			<Time>106.4998</Time>
		</Step>
		<Step>
			<WhichFoot>R</WhichFoot>
			<Time>107.1306</Time>
		</Step>
		<Step>
			<WhichFoot>L</WhichFoot>
			<Time>107.6395</Time>
		</Step>
		<Step>
			<WhichFoot>R</WhichFoot>
			<Time>108.2397</Time>
		</Step>
		<Step>
			<WhichFoot>L</WhichFoot>
			<Time>108.7518</Time>
		</Step>
		<Step>
			<WhichFoot>R</WhichFoot>
			<Time>109.3798</Time>
		</Step>
		<Step>
			<WhichFoot>L</WhichFoot>
			<Time>109.8634</Time>
		</Step>
		<Step>
			<WhichFoot>R</WhichFoot>
			<Time>110.5206</Time>
		</Step>
		<Step>
			<WhichFoot>L</WhichFoot>
			<Time>111.0004</Time>
		</Step>
		<Step>
			<WhichFoot>R</WhichFoot>
			<Time>111.6308</Time>
		</Step>
		<Step>
			<WhichFoot>L</WhichFoot>
			<Time>112.1401</Time>
		</Step>
		<Step>
			<WhichFoot>R</WhichFoot>
			<Time>112.8301</Time>
		</Step>
		<Step>
			<WhichFoot>L</WhichFoot>
			<Time>113.3093</Time>
		</Step>
		<Step>
			<WhichFoot>R</WhichFoot>
			<Time>113.8804</Time>
		</Step>
		<Step>
			<WhichFoot>L</WhichFoot>
			<Time>114.4510</Time>
		</Step>
		<Step>
			<WhichFoot>R</WhichFoot>
			<Time>115.0811</Time>
		</Step>
		<Step>
			<WhichFoot>L</WhichFoot>
			<Time>115.5603</Time>
		</Step>
		<Step>
			<WhichFoot>R</WhichFoot>
			<Time>116.1907</Time>
		</Step>
		<Step>
			<WhichFoot>L</WhichFoot>
			<Time>116.7015</Time>
		</Step>
		<Step>
			<WhichFoot>R</WhichFoot>
			<Time>117.3368</Time>
		</Step>
		<Step>
			<WhichFoot>L</WhichFoot>
			<Time>117.8695</Time>
		</Step>
		<Step>
			<WhichFoot>R</WhichFoot>
			<Time>118.4399</Time>
		</Step>
		<Step>
			<WhichFoot>L</WhichFoot>
			<Time>118.9491</Time>
		</Step>
		<Step>
			<WhichFoot>R</WhichFoot>
			<Time>119.6165</Time>
		</Step>
		<Step>
			<WhichFoot>L</WhichFoot>
			<Time>120.1205</Time>
		</Step>
		<Step>
			<WhichFoot>R</WhichFoot>
			<Time>120.6973</Time>
		</Step>
		<Step>
			<WhichFoot>L</WhichFoot>
			<Time>121.2002</Time>
		</Step>
		<Step>
			<WhichFoot>R</WhichFoot>
			<Time>121.8600</Time>
		</Step>
		<Step>
			<WhichFoot>L</WhichFoot>
			<Time>122.3097</Time>
		</Step>
		<Step>
			<WhichFoot>R</WhichFoot>
			<Time>122.9396</Time>
		</Step>
		<Step>
			<WhichFoot>L</WhichFoot>
			<Time>123.4798</Time>
		</Step>
		<Step>
			<WhichFoot>R</WhichFoot>
			<Time>124.1405</Time>
		</Step>
		<Step>
			<WhichFoot>L</WhichFoot>
			<Time>124.6617</Time>
		</Step>
		<Step>
			<WhichFoot>R</WhichFoot>
			<Time>125.2806</Time>
		</Step>
		<Step>
			<WhichFoot>L</WhichFoot>
			<Time>125.7914</Time>
		</Step>
		<Step>
			<WhichFoot>R</WhichFoot>
			<Time>126.4212</Time>
		</Step>
		<Step>
			<WhichFoot>L</WhichFoot>
			<Time>126.9415</Time>
		</Step>
		<Step>
			<WhichFoot>R</WhichFoot>
			<Time>127.5598</Time>
		</Step>
		<Step>
			<WhichFoot>L</WhichFoot>
			<Time>128.0698</Time>
		</Step>
		<Step>
			<WhichFoot>R</WhichFoot>
			<Time>128.6701</Time>
		</Step>
		<Step>
			<WhichFoot>L</WhichFoot>
			<Time>129.1497</Time>
		</Step>
		<Step>
			<WhichFoot>R</WhichFoot>
			<Time>129.7803</Time>
		</Step>
		<Step>
			<WhichFoot>L</WhichFoot>
			<Time>130.2913</Time>
		</Step>
		<Step>
			<WhichFoot>R</WhichFoot>
			<Time>130.9252</Time>
		</Step>
		<Step>
			<WhichFoot>L</WhichFoot>
			<Time>131.4291</Time>
		</Step>
		<Step>
			<WhichFoot>R</WhichFoot>
			<Time>132.0315</Time>
		</Step>
		<Step>
			<WhichFoot>L</WhichFoot>
			<Time>132.5102</Time>
		</Step>
		<Step>
			<WhichFoot>R</WhichFoot>
			<Time>133.2011</Time>
		</Step>
		<Step>
			<WhichFoot>L</WhichFoot>
			<Time>133.6802</Time>
		</Step>
		<Step>
			<WhichFoot>R</WhichFoot>
			<Time>134.3405</Time>
		</Step>
		<Step>
			<WhichFoot>L</WhichFoot>
			<Time>134.7902</Time>
		</Step>
		<Step>
			<WhichFoot>R</WhichFoot>
			<Time>135.4621</Time>
		</Step>
		<Step>
			<WhichFoot>L</WhichFoot>
			<Time>135.9601</Time>
		</Step>
		<Step>
			<WhichFoot>R</WhichFoot>
			<Time>136.5608</Time>
		</Step>
		<Step>
			<WhichFoot>L</WhichFoot>
			<Time>137.0407</Time>
		</Step>
		<Step>
			<WhichFoot>R</WhichFoot>
			<Time>137.6998</Time>
		</Step>
		<Step>
			<WhichFoot>L</WhichFoot>
			<Time>138.1498</Time>
		</Step>
		<Step>
			<WhichFoot>R</WhichFoot>
			<Time>138.8408</Time>
		</Step>
		<Step>
			<WhichFoot>L</WhichFoot>
			<Time>139.3494</Time>
		</Step>
		<Step>
			<WhichFoot>R</WhichFoot>
			<Time>140.0397</Time>
		</Step>
		<Step>
			<WhichFoot>L</WhichFoot>
			<Time>140.5503</Time>
		</Step>
	</Steps>
	<Features>
		<Feature>
			<StartTime>90.973043</StartTime>
			<EndTime>97.206377</EndTime>
			<Description>The participant moved to the right side of corridor in order to avoid other people walking towards him</Description>
		</Feature>
	</Features>
</PathSegment>
<PathSegment>
	<PathSegmentID>8</PathSegmentID>
	<SpatialSegmentID>9-6</SpatialSegmentID>
	<StartTime>141.0730</StartTime>
	<EndTime>144.2730</EndTime>
	<NSteps>5</NSteps>
	<Direction>TurnWtoN</Direction>
	<TurnTime>142.7000</TurnTime>
	<TurnInDegrees>-90</TurnInDegrees>
	<Steps>
		<Step>
			<WhichFoot>R</WhichFoot>
			<Time>141.2999</Time>
		</Step>
		<Step>
			<WhichFoot>L</WhichFoot>
			<Time>141.8399</Time>
		</Step>
		<Step>
			<WhichFoot>R</WhichFoot>
			<Time>142.5661</Time>
		</Step>
		<Step>
			<WhichFoot>L</WhichFoot>
			<Time>143.1331</Time>
		</Step>
		<Step>
			<WhichFoot>R</WhichFoot>
			<Time>143.8515</Time>
		</Step>
	</Steps>
</PathSegment>
<PathSegment>
	<PathSegmentID>9</PathSegmentID>
	<SpatialSegmentID>6</SpatialSegmentID>
	<StartTime>144.2730</StartTime>
	<EndTime>152.0064</EndTime>
	<NSteps>13</NSteps>
	<Direction>N</Direction>
	<Steps>
		<Step>
			<WhichFoot>L</WhichFoot>
			<Time>144.3897</Time>
		</Step>
		<Step>
			<WhichFoot>R</WhichFoot>
			<Time>145.1099</Time>
		</Step>
		<Step>
			<WhichFoot>L</WhichFoot>
			<Time>145.6807</Time>
		</Step>
		<Step>
			<WhichFoot>R</WhichFoot>
			<Time>146.4025</Time>
		</Step>
		<Step>
			<WhichFoot>L</WhichFoot>
			<Time>146.8800</Time>
		</Step>
		<Step>
			<WhichFoot>R</WhichFoot>
			<Time>147.5767</Time>
		</Step>
		<Step>
			<WhichFoot>L</WhichFoot>
			<Time>148.0804</Time>
		</Step>
		<Step>
			<WhichFoot>R</WhichFoot>
			<Time>148.7103</Time>
		</Step>
		<Step>
			<WhichFoot>L</WhichFoot>
			<Time>149.2512</Time>
		</Step>
		<Step>
			<WhichFoot>R</WhichFoot>
			<Time>149.8807</Time>
		</Step>
		<Step>
			<WhichFoot>L</WhichFoot>
			<Time>150.3898</Time>
		</Step>
		<Step>
			<WhichFoot>R</WhichFoot>
			<Time>151.0799</Time>
		</Step>
		<Step>
			<WhichFoot>L</WhichFoot>
			<Time>151.5899</Time>
		</Step>
	</Steps>
</PathSegment>
<PathSegment>
	<PathSegmentID>10</PathSegmentID>
	<SpatialSegmentID>6-2</SpatialSegmentID>
	<StartTime>152.0064</StartTime>
	<EndTime>154.5730</EndTime>
	<NSteps>4</NSteps>
	<Direction>TurnNtoW</Direction>
	<TurnTime>154.0000</TurnTime>
	<TurnInDegrees>90</TurnInDegrees>
	<Steps>
		<Step>
			<WhichFoot>R</WhichFoot>
			<Time>152.2595</Time>
		</Step>
		<Step>
			<WhichFoot>L</WhichFoot>
			<Time>152.7303</Time>
		</Step>
		<Step>
			<WhichFoot>R</WhichFoot>
			<Time>153.4229</Time>
		</Step>
		<Step>
			<WhichFoot>L</WhichFoot>
			<Time>154.0520</Time>
		</Step>
	</Steps>
</PathSegment>
<PathSegment>
	<PathSegmentID>11</PathSegmentID>
	<SpatialSegmentID>2</SpatialSegmentID>
	<StartTime>154.5730</StartTime>
	<EndTime>193.0730</EndTime>
	<NSteps>67</NSteps>
	<Direction>W</Direction>
	<Steps>
		<Step>
			<WhichFoot>R</WhichFoot>
			<Time>154.7825</Time>
		</Step>
		<Step>
			<WhichFoot>L</WhichFoot>
			<Time>155.3717</Time>
		</Step>
		<Step>
			<WhichFoot>R</WhichFoot>
			<Time>156.0633</Time>
		</Step>
		<Step>
			<WhichFoot>L</WhichFoot>
			<Time>156.6598</Time>
		</Step>
		<Step>
			<WhichFoot>R</WhichFoot>
			<Time>157.3500</Time>
		</Step>
		<Step>
			<WhichFoot>L</WhichFoot>
			<Time>157.8599</Time>
		</Step>
		<Step>
			<WhichFoot>R</WhichFoot>
			<Time>158.4937</Time>
		</Step>
		<Step>
			<WhichFoot>L</WhichFoot>
			<Time>158.9998</Time>
		</Step>
		<Step>
			<WhichFoot>R</WhichFoot>
			<Time>159.6300</Time>
		</Step>
		<Step>
			<WhichFoot>L</WhichFoot>
			<Time>160.1702</Time>
		</Step>
		<Step>
			<WhichFoot>R</WhichFoot>
			<Time>160.7770</Time>
		</Step>
		<Step>
			<WhichFoot>L</WhichFoot>
			<Time>161.2798</Time>
		</Step>
		<Step>
			<WhichFoot>R</WhichFoot>
			<Time>161.9422</Time>
		</Step>
		<Step>
			<WhichFoot>L</WhichFoot>
			<Time>162.4515</Time>
		</Step>
		<Step>
			<WhichFoot>R</WhichFoot>
			<Time>163.1170</Time>
		</Step>
		<Step>
			<WhichFoot>L</WhichFoot>
			<Time>163.5600</Time>
		</Step>
		<Step>
			<WhichFoot>R</WhichFoot>
			<Time>164.2316</Time>
		</Step>
		<Step>
			<WhichFoot>L</WhichFoot>
			<Time>164.7311</Time>
		</Step>
		<Step>
			<WhichFoot>R</WhichFoot>
			<Time>165.3758</Time>
		</Step>
		<Step>
			<WhichFoot>L</WhichFoot>
			<Time>165.8409</Time>
		</Step>
		<Step>
			<WhichFoot>R</WhichFoot>
			<Time>166.4915</Time>
		</Step>
		<Step>
			<WhichFoot>L</WhichFoot>
			<Time>166.9799</Time>
		</Step>
		<Step>
			<WhichFoot>R</WhichFoot>
			<Time>167.6352</Time>
		</Step>
		<Step>
			<WhichFoot>L</WhichFoot>
			<Time>168.1495</Time>
		</Step>
		<Step>
			<WhichFoot>R</WhichFoot>
			<Time>168.8093</Time>
		</Step>
		<Step>
			<WhichFoot>L</WhichFoot>
			<Time>169.1854</Time>
		</Step>
		<Step>
			<WhichFoot>R</WhichFoot>
			<Time>169.8339</Time>
		</Step>
		<Step>
			<WhichFoot>L</WhichFoot>
			<Time>170.2603</Time>
		</Step>
		<Step>
			<WhichFoot>R</WhichFoot>
			<Time>170.9487</Time>
		</Step>
		<Step>
			<WhichFoot>L</WhichFoot>
			<Time>171.4194</Time>
		</Step>
		<Step>
			<WhichFoot>R</WhichFoot>
			<Time>172.0924</Time>
		</Step>
		<Step>
			<WhichFoot>L</WhichFoot>
			<Time>172.5304</Time>
		</Step>
		<Step>
			<WhichFoot>R</WhichFoot>
			<Time>173.2025</Time>
		</Step>
		<Step>
			<WhichFoot>L</WhichFoot>
			<Time>173.6403</Time>
		</Step>
		<Step>
			<WhichFoot>R</WhichFoot>
			<Time>174.4025</Time>
		</Step>
		<Step>
			<WhichFoot>L</WhichFoot>
			<Time>174.7800</Time>
		</Step>
		<Step>
			<WhichFoot>R</WhichFoot>
			<Time>175.4596</Time>
		</Step>
		<Step>
			<WhichFoot>L</WhichFoot>
			<Time>175.9198</Time>
		</Step>
		<Step>
			<WhichFoot>R</WhichFoot>
			<Time>176.5929</Time>
		</Step>
		<Step>
			<WhichFoot>L</WhichFoot>
			<Time>177.0607</Time>
		</Step>
		<Step>
			<WhichFoot>R</WhichFoot>
			<Time>177.7029</Time>
		</Step>
		<Step>
			<WhichFoot>L</WhichFoot>
			<Time>178.1702</Time>
		</Step>
		<Step>
			<WhichFoot>R</WhichFoot>
			<Time>178.8728</Time>
		</Step>
		<Step>
			<WhichFoot>L</WhichFoot>
			<Time>179.3414</Time>
		</Step>
		<Step>
			<WhichFoot>R</WhichFoot>
			<Time>179.9857</Time>
		</Step>
		<Step>
			<WhichFoot>L</WhichFoot>
			<Time>180.4517</Time>
		</Step>
		<Step>
			<WhichFoot>R</WhichFoot>
			<Time>181.0925</Time>
		</Step>
		<Step>
			<WhichFoot>L</WhichFoot>
			<Time>181.5603</Time>
		</Step>
		<Step>
			<WhichFoot>R</WhichFoot>
			<Time>182.2938</Time>
		</Step>
		<Step>
			<WhichFoot>L</WhichFoot>
			<Time>182.7441</Time>
		</Step>
		<Step>
			<WhichFoot>R</WhichFoot>
			<Time>183.4329</Time>
		</Step>
		<Step>
			<WhichFoot>L</WhichFoot>
			<Time>183.9312</Time>
		</Step>
		<Step>
			<WhichFoot>R</WhichFoot>
			<Time>184.6321</Time>
		</Step>
		<Step>
			<WhichFoot>L</WhichFoot>
			<Time>185.1008</Time>
		</Step>
		<Step>
			<WhichFoot>R</WhichFoot>
			<Time>185.8042</Time>
		</Step>
		<Step>
			<WhichFoot>L</WhichFoot>
			<Time>186.3002</Time>
		</Step>
		<Step>
			<WhichFoot>R</WhichFoot>
			<Time>187.0044</Time>
		</Step>
		<Step>
			<WhichFoot>L</WhichFoot>
			<Time>187.4408</Time>
		</Step>
		<Step>
			<WhichFoot>R</WhichFoot>
			<Time>188.1432</Time>
		</Step>
		<Step>
			<WhichFoot>L</WhichFoot>
			<Time>188.5816</Time>
		</Step>
		<Step>
			<WhichFoot>R</WhichFoot>
			<Time>189.2829</Time>
		</Step>
		<Step>
			<WhichFoot>L</WhichFoot>
			<Time>189.7234</Time>
		</Step>
		<Step>
			<WhichFoot>R</WhichFoot>
			<Time>190.4832</Time>
		</Step>
		<Step>
			<WhichFoot>L</WhichFoot>
			<Time>190.9020</Time>
		</Step>
		<Step>
			<WhichFoot>R</WhichFoot>
			<Time>191.6222</Time>
		</Step>
		<Step>
			<WhichFoot>L</WhichFoot>
			<Time>192.0637</Time>
		</Step>
		<Step>
			<WhichFoot>R</WhichFoot>
			<Time>192.7922</Time>
		</Step>
	</Steps>
</PathSegment>
<PathSegment>
	<PathSegmentID>12</PathSegmentID>
	<SpatialSegmentID>2-5</SpatialSegmentID>
	<StartTime>193.0730</StartTime>
	<EndTime>196.9397</EndTime>
	<NSteps>5</NSteps>
	<Direction>TurnWtoS</Direction>
	<TurnTime>194.7000</TurnTime>
	<TurnInDegrees>90</TurnInDegrees>
	<Steps>
		<Step>
			<WhichFoot>L</WhichFoot>
			<Time>193.2640</Time>
		</Step>
		<Step>
			<WhichFoot>R</WhichFoot>
			<Time>194.0233</Time>
		</Step>
		<Step>
			<WhichFoot>L</WhichFoot>
			<Time>194.5825</Time>
		</Step>
		<Step>
			<WhichFoot>R</WhichFoot>
			<Time>195.8000</Time>
		</Step>
		<Step>
			<WhichFoot>L</WhichFoot>
			<Time>196.4108</Time>
		</Step>
	</Steps>
</PathSegment>
<PathSegment>
	<PathSegmentID>13</PathSegmentID>
	<SpatialSegmentID>5</SpatialSegmentID>
	<StartTime>196.9397</StartTime>
	<EndTime>203.3064</EndTime>
	<NSteps>11</NSteps>
	<Direction>S</Direction>
	<Steps>
		<Step>
			<WhichFoot>R</WhichFoot>
			<Time>197.2323</Time>
		</Step>
		<Step>
			<WhichFoot>L</WhichFoot>
			<Time>197.7315</Time>
		</Step>
		<Step>
			<WhichFoot>R</WhichFoot>
			<Time>198.4993</Time>
		</Step>
		<Step>
			<WhichFoot>L</WhichFoot>
			<Time>198.9902</Time>
		</Step>
		<Step>
			<WhichFoot>R</WhichFoot>
			<Time>199.7230</Time>
		</Step>
		<Step>
			<WhichFoot>L</WhichFoot>
			<Time>200.1901</Time>
		</Step>
		<Step>
			<WhichFoot>R</WhichFoot>
			<Time>200.8330</Time>
		</Step>
		<Step>
			<WhichFoot>L</WhichFoot>
			<Time>201.3009</Time>
		</Step>
		<Step>
			<WhichFoot>R</WhichFoot>
			<Time>201.9801</Time>
		</Step>
		<Step>
			<WhichFoot>L</WhichFoot>
			<Time>202.4138</Time>
		</Step>
		<Step>
			<WhichFoot>R</WhichFoot>
			<Time>203.0822</Time>
		</Step>
	</Steps>
</PathSegment>
<PathSegment>
	<PathSegmentID>14</PathSegmentID>
	<SpatialSegmentID>5-8</SpatialSegmentID>
	<StartTime>203.3064</StartTime>
	<EndTime>208.7064</EndTime>
	<NSteps>7</NSteps>
	<Direction>TurnStoE</Direction>
	<TurnTime>208.2000</TurnTime>
	<TurnInDegrees>90</TurnInDegrees>
	<Steps>
		<Step>
			<WhichFoot>L</WhichFoot>
			<Time>203.5806</Time>
		</Step>
		<Step>
			<WhichFoot>R</WhichFoot>
			<Time>204.2223</Time>
		</Step>
		<Step>
			<WhichFoot>L</WhichFoot>
			<Time>204.6920</Time>
		</Step>
		<Step>
			<WhichFoot>R</WhichFoot>
			<Time>205.5000</Time>
		</Step>
		<Step>
			<WhichFoot>L</WhichFoot>
			<Time>206.8204</Time>
		</Step>
		<Step>
			<WhichFoot>R</WhichFoot>
			<Time>207.7372</Time>
		</Step>
		<Step>
			<WhichFoot>L</WhichFoot>
			<Time>208.2898</Time>
		</Step>
	</Steps>
</PathSegment>
<PathSegment>
	<PathSegmentID>15</PathSegmentID>
	<SpatialSegmentID>8</SpatialSegmentID>
	<StartTime>208.7064</StartTime>
	<EndTime>244.7730</EndTime>
	<NSteps>63</NSteps>
	<Direction>E</Direction>
	<Steps>
		<Step>
			<WhichFoot>R</WhichFoot>
			<Time>209.0223</Time>
		</Step>
		<Step>
			<WhichFoot>L</WhichFoot>
			<Time>209.5502</Time>
		</Step>
		<Step>
			<WhichFoot>R</WhichFoot>
			<Time>210.2228</Time>
		</Step>
		<Step>
			<WhichFoot>L</WhichFoot>
			<Time>210.7020</Time>
		</Step>
		<Step>
			<WhichFoot>R</WhichFoot>
			<Time>211.3923</Time>
		</Step>
		<Step>
			<WhichFoot>L</WhichFoot>
			<Time>211.8604</Time>
		</Step>
		<Step>
			<WhichFoot>R</WhichFoot>
			<Time>212.5942</Time>
		</Step>
		<Step>
			<WhichFoot>L</WhichFoot>
			<Time>213.0632</Time>
		</Step>
		<Step>
			<WhichFoot>R</WhichFoot>
			<Time>213.7623</Time>
		</Step>
		<Step>
			<WhichFoot>L</WhichFoot>
			<Time>214.1796</Time>
		</Step>
		<Step>
			<WhichFoot>R</WhichFoot>
			<Time>214.8192</Time>
		</Step>
		<Step>
			<WhichFoot>L</WhichFoot>
			<Time>215.3102</Time>
		</Step>
		<Step>
			<WhichFoot>R</WhichFoot>
			<Time>215.9531</Time>
		</Step>
		<Step>
			<WhichFoot>L</WhichFoot>
			<Time>216.4512</Time>
		</Step>
		<Step>
			<WhichFoot>R</WhichFoot>
			<Time>217.1529</Time>
		</Step>
		<Step>
			<WhichFoot>L</WhichFoot>
			<Time>217.5906</Time>
		</Step>
		<Step>
			<WhichFoot>R</WhichFoot>
			<Time>218.2641</Time>
		</Step>
		<Step>
			<WhichFoot>L</WhichFoot>
			<Time>218.7611</Time>
		</Step>
		<Step>
			<WhichFoot>R</WhichFoot>
			<Time>219.4029</Time>
		</Step>
		<Step>
			<WhichFoot>L</WhichFoot>
			<Time>219.9002</Time>
		</Step>
		<Step>
			<WhichFoot>R</WhichFoot>
			<Time>220.5427</Time>
		</Step>
		<Step>
			<WhichFoot>L</WhichFoot>
			<Time>221.1023</Time>
		</Step>
		<Step>
			<WhichFoot>R</WhichFoot>
			<Time>221.7123</Time>
		</Step>
		<Step>
			<WhichFoot>L</WhichFoot>
			<Time>222.1803</Time>
		</Step>
		<Step>
			<WhichFoot>R</WhichFoot>
			<Time>222.8522</Time>
		</Step>
		<Step>
			<WhichFoot>L</WhichFoot>
			<Time>223.3021</Time>
		</Step>
		<Step>
			<WhichFoot>R</WhichFoot>
			<Time>223.9923</Time>
		</Step>
		<Step>
			<WhichFoot>L</WhichFoot>
			<Time>224.4319</Time>
		</Step>
		<Step>
			<WhichFoot>R</WhichFoot>
			<Time>225.1622</Time>
		</Step>
		<Step>
			<WhichFoot>L</WhichFoot>
			<Time>225.5809</Time>
		</Step>
		<Step>
			<WhichFoot>R</WhichFoot>
			<Time>226.3414</Time>
		</Step>
		<Step>
			<WhichFoot>L</WhichFoot>
			<Time>226.7839</Time>
		</Step>
		<Step>
			<WhichFoot>R</WhichFoot>
			<Time>227.5074</Time>
		</Step>
		<Step>
			<WhichFoot>L</WhichFoot>
			<Time>227.9822</Time>
		</Step>
		<Step>
			<WhichFoot>R</WhichFoot>
			<Time>228.6132</Time>
		</Step>
		<Step>
			<WhichFoot>L</WhichFoot>
			<Time>229.1108</Time>
		</Step>
		<Step>
			<WhichFoot>R</WhichFoot>
			<Time>229.8135</Time>
		</Step>
		<Step>
			<WhichFoot>L</WhichFoot>
			<Time>230.2207</Time>
		</Step>
		<Step>
			<WhichFoot>R</WhichFoot>
			<Time>230.8632</Time>
		</Step>
		<Step>
			<WhichFoot>L</WhichFoot>
			<Time>231.3913</Time>
		</Step>
		<Step>
			<WhichFoot>R</WhichFoot>
			<Time>232.0637</Time>
		</Step>
		<Step>
			<WhichFoot>L</WhichFoot>
			<Time>232.5313</Time>
		</Step>
		<Step>
			<WhichFoot>R</WhichFoot>
			<Time>233.2023</Time>
		</Step>
		<Step>
			<WhichFoot>L</WhichFoot>
			<Time>233.6398</Time>
		</Step>
		<Step>
			<WhichFoot>R</WhichFoot>
			<Time>234.3128</Time>
		</Step>
		<Step>
			<WhichFoot>L</WhichFoot>
			<Time>234.7503</Time>
		</Step>
		<Step>
			<WhichFoot>R</WhichFoot>
			<Time>235.4234</Time>
		</Step>
		<Step>
			<WhichFoot>L</WhichFoot>
			<Time>235.8629</Time>
		</Step>
		<Step>
			<WhichFoot>R</WhichFoot>
			<Time>236.5323</Time>
		</Step>
		<Step>
			<WhichFoot>L</WhichFoot>
			<Time>237.0316</Time>
		</Step>
		<Step>
			<WhichFoot>R</WhichFoot>
			<Time>237.6743</Time>
		</Step>
		<Step>
			<WhichFoot>L</WhichFoot>
			<Time>238.1113</Time>
		</Step>
		<Step>
			<WhichFoot>R</WhichFoot>
			<Time>238.8210</Time>
		</Step>
		<Step>
			<WhichFoot>L</WhichFoot>
			<Time>239.2207</Time>
		</Step>
		<Step>
			<WhichFoot>R</WhichFoot>
			<Time>239.9221</Time>
		</Step>
		<Step>
			<WhichFoot>L</WhichFoot>
			<Time>240.3048</Time>
		</Step>
		<Step>
			<WhichFoot>R</WhichFoot>
			<Time>241.0329</Time>
		</Step>
		<Step>
			<WhichFoot>L</WhichFoot>
			<Time>241.4698</Time>
		</Step>
		<Step>
			<WhichFoot>R</WhichFoot>
			<Time>242.1434</Time>
		</Step>
		<Step>
			<WhichFoot>L</WhichFoot>
			<Time>242.6413</Time>
		</Step>
		<Step>
			<WhichFoot>R</WhichFoot>
			<Time>243.4337</Time>
		</Step>
		<Step>
			<WhichFoot>L</WhichFoot>
			<Time>244.0215</Time>
		</Step>
		<Step>
			<WhichFoot>R</WhichFoot>
			<Time>244.7824</Time>
		</Step>
	</Steps>
</PathSegment>
</Segments>
</root>
